redblack_test_1414/__init__.py
redblack_test_1414/example.py
redblack_test_1414-0.1.1.dist-info/LICENSE
redblack_test_1414-0.1.1.dist-info/METADATA
redblack_test_1414-0.1.1.dist-info/WHEEL
redblack_test_1414-0.1.1.dist-info/top_level.txt
redblack_test_1414-0.1.1.dist-info/RECORD
